{
    "2015": {
        "Alabama": {
            "g_total": "1964105",
            "id": 1,
            "subj_total": {
                "16 to 19 years": "65102",
                "20 to 24 years": "195768",
                "25 to 44 years": "852098",
                "45 to 54 years": "425704",
                "55 to 59 years": "194128",
                "60 to 64 years": "127427",
                "65 years and over": "103878",
                "Car, truck, or van - drove alone:": "1677578"
            },
            "worked_at_home": {
                "16 to 19 years": "991",
                "20 to 24 years": "4119",
                "25 to 44 years": "26498",
                "45 to 54 years": "11980",
                "55 to 59 years": "6186",
                "60 to 64 years": "6866",
                "65 years and over": "7117",
                "total": "63757"
            }
        },
        "Alaska": {
            "g_total": "371382",
            "id": 2,
            "subj_total": {
                "16 to 19 years": "13734",
                "20 to 24 years": "46042",
                "25 to 44 years": "163259",
                "45 to 54 years": "70432",
                "55 to 59 years": "36942",
                "60 to 64 years": "25929",
                "65 years and over": "15044",
                "Car, truck, or van - drove alone:": "249521"
            },
            "worked_at_home": {
                "16 to 19 years": "534",
                "20 to 24 years": "773",
                "25 to 44 years": "5396",
                "45 to 54 years": "3153",
                "55 to 59 years": "2696",
                "60 to 64 years": "1839",
                "65 years and over": "1704",
                "total": "16095"
            }
        },
        "Arizona": {
            "g_total": "2872284",
            "id": 4,
            "subj_total": {
                "16 to 19 years": "106945",
                "20 to 24 years": "307621",
                "25 to 44 years": "1265547",
                "45 to 54 years": "607124",
                "55 to 59 years": "256043",
                "60 to 64 years": "186127",
                "65 years and over": "142877",
                "Car, truck, or van - drove alone:": "2214950"
            },
            "worked_at_home": {
                "16 to 19 years": "2529",
                "20 to 24 years": "6164",
                "25 to 44 years": "55688",
                "45 to 54 years": "40492",
                "55 to 59 years": "20278",
                "60 to 64 years": "16098",
                "65 years and over": "18432",
                "total": "159681"
            }
        },
        "Arkansas": {
            "g_total": "1249200",
            "id": 5,
            "subj_total": {
                "16 to 19 years": "47208",
                "20 to 24 years": "127426",
                "25 to 44 years": "542601",
                "45 to 54 years": "265773",
                "55 to 59 years": "117787",
                "60 to 64 years": "78866",
                "65 years and over": "69539",
                "Car, truck, or van - drove alone:": "1034815"
            },
            "worked_at_home": {
                "16 to 19 years": "1021",
                "20 to 24 years": "1473",
                "25 to 44 years": "13913",
                "45 to 54 years": "8839",
                "55 to 59 years": "5622",
                "60 to 64 years": "2982",
                "65 years and over": "4520",
                "total": "38370"
            }
        },
        "California": {
            "g_total": "17630992",
            "id": 6,
            "subj_total": {
                "16 to 19 years": "445447",
                "20 to 24 years": "1748032",
                "25 to 44 years": "8080703",
                "45 to 54 years": "3809275",
                "55 to 59 years": "1607846",
                "60 to 64 years": "1101651",
                "65 years and over": "838038",
                "Car, truck, or van - drove alone:": "13031458"
            },
            "worked_at_home": {
                "16 to 19 years": "14594",
                "20 to 24 years": "42969",
                "25 to 44 years": "350663",
                "45 to 54 years": "248618",
                "55 to 59 years": "114881",
                "60 to 64 years": "93575",
                "65 years and over": "104739",
                "total": "970039"
            }
        },
        "Colorado": {
            "g_total": "2731235",
            "id": 8,
            "subj_total": {
                "16 to 19 years": "98118",
                "20 to 24 years": "272081",
                "25 to 44 years": "1237594",
                "45 to 54 years": "561208",
                "55 to 59 years": "248936",
                "60 to 64 years": "183169",
                "65 years and over": "130129",
                "Car, truck, or van - drove alone:": "2089507"
            },
            "worked_at_home": {
                "16 to 19 years": "3199",
                "20 to 24 years": "8181",
                "25 to 44 years": "76546",
                "45 to 54 years": "47871",
                "55 to 59 years": "23211",
                "60 to 64 years": "17683",
                "65 years and over": "18213",
                "total": "194904"
            }
        },
        "Connecticut": {
            "g_total": "1741224",
            "id": 9,
            "subj_total": {
                "16 to 19 years": "62290",
                "20 to 24 years": "161019",
                "25 to 44 years": "670496",
                "45 to 54 years": "402449",
                "55 to 59 years": "195894",
                "60 to 64 years": "140475",
                "65 years and over": "108601",
                "Car, truck, or van - drove alone:": "1389816"
            },
            "worked_at_home": {
                "16 to 19 years": "2422",
                "20 to 24 years": "3762",
                "25 to 44 years": "25555",
                "45 to 54 years": "23951",
                "55 to 59 years": "11268",
                "60 to 64 years": "8511",
                "65 years and over": "9410",
                "total": "84879"
            }
        },
        "Delaware": {
            "g_total": "440156",
            "id": 10,
            "subj_total": {
                "16 to 19 years": "14512",
                "20 to 24 years": "41805",
                "25 to 44 years": "181758",
                "45 to 54 years": "99622",
                "55 to 59 years": "45982",
                "60 to 64 years": "31261",
                "65 years and over": "25216",
                "Car, truck, or van - drove alone:": "359048"
            },
            "worked_at_home": {
                "16 to 19 years": "122",
                "20 to 24 years": "626",
                "25 to 44 years": "5649",
                "45 to 54 years": "6419",
                "55 to 59 years": "2991",
                "60 to 64 years": "2405",
                "65 years and over": "2666",
                "total": "20878"
            }
        },
        "District of Columbia": {
            "g_total": "839206",
            "id": 11,
            "subj_total": {
                "16 to 19 years": "10433",
                "20 to 24 years": "52887",
                "25 to 44 years": "414465",
                "45 to 54 years": "189621",
                "55 to 59 years": "80057",
                "60 to 64 years": "52136",
                "65 years and over": "39607",
                "Car, truck, or van - drove alone:": "350625"
            },
            "worked_at_home": {
                "16 to 19 years": "934",
                "20 to 24 years": "1558",
                "25 to 44 years": "9715",
                "45 to 54 years": "3915",
                "55 to 59 years": "2115",
                "60 to 64 years": "1365",
                "65 years and over": "1927",
                "total": "21529"
            }
        },
        "Florida": {
            "g_total": "8827805",
            "id": 12,
            "subj_total": {
                "16 to 19 years": "236082",
                "20 to 24 years": "808383",
                "25 to 44 years": "3771433",
                "45 to 54 years": "2003144",
                "55 to 59 years": "861020",
                "60 to 64 years": "622424",
                "65 years and over": "525319",
                "Car, truck, or van - drove alone:": "7042650"
            },
            "worked_at_home": {
                "16 to 19 years": "7886",
                "20 to 24 years": "17957",
                "25 to 44 years": "166670",
                "45 to 54 years": "130590",
                "55 to 59 years": "55866",
                "60 to 64 years": "52390",
                "65 years and over": "61948",
                "total": "493307"
            }
        },
        "Georgia": {
            "g_total": "4555994",
            "id": 13,
            "subj_total": {
                "16 to 19 years": "143798",
                "20 to 24 years": "439575",
                "25 to 44 years": "2062108",
                "45 to 54 years": "1024026",
                "55 to 59 years": "413803",
                "60 to 64 years": "267364",
                "65 years and over": "205320",
                "Car, truck, or van - drove alone:": "3630538"
            },
            "worked_at_home": {
                "16 to 19 years": "5168",
                "20 to 24 years": "12054",
                "25 to 44 years": "87637",
                "45 to 54 years": "61181",
                "55 to 59 years": "28374",
                "60 to 64 years": "17408",
                "65 years and over": "20146",
                "total": "231968"
            }
        },
        "Hawaii": {
            "g_total": "705741",
            "id": 15,
            "subj_total": {
                "16 to 19 years": "20069",
                "20 to 24 years": "74285",
                "25 to 44 years": "309125",
                "45 to 54 years": "138647",
                "55 to 59 years": "69754",
                "60 to 64 years": "48100",
                "65 years and over": "45761",
                "Car, truck, or van - drove alone:": "475556"
            },
            "worked_at_home": {
                "16 to 19 years": "1120",
                "20 to 24 years": "3315",
                "25 to 44 years": "11594",
                "45 to 54 years": "5635",
                "55 to 59 years": "3671",
                "60 to 64 years": "3316",
                "65 years and over": "3965",
                "total": "32616"
            }
        },
        "Idaho": {
            "g_total": "714037",
            "id": 16,
            "subj_total": {
                "16 to 19 years": "32587",
                "20 to 24 years": "74229",
                "25 to 44 years": "309012",
                "45 to 54 years": "144892",
                "55 to 59 years": "68766",
                "60 to 64 years": "46408",
                "65 years and over": "38143",
                "Car, truck, or van - drove alone:": "551719"
            },
            "worked_at_home": {
                "16 to 19 years": "1253",
                "20 to 24 years": "3030",
                "25 to 44 years": "15695",
                "45 to 54 years": "10806",
                "55 to 59 years": "4996",
                "60 to 64 years": "3726",
                "65 years and over": "5731",
                "total": "45237"
            }
        },
        "Illinois": {
            "g_total": "6082035",
            "id": 17,
            "subj_total": {
                "16 to 19 years": "201144",
                "20 to 24 years": "577933",
                "25 to 44 years": "2652883",
                "45 to 54 years": "1335568",
                "55 to 59 years": "606799",
                "60 to 64 years": "410099",
                "65 years and over": "297609",
                "Car, truck, or van - drove alone:": "4467523"
            },
            "worked_at_home": {
                "16 to 19 years": "4465",
                "20 to 24 years": "12613",
                "25 to 44 years": "103298",
                "45 to 54 years": "63656",
                "55 to 59 years": "32436",
                "60 to 64 years": "26206",
                "65 years and over": "25760",
                "total": "268434"
            }
        },
        "Indiana": {
            "g_total": "3012416",
            "id": 18,
            "subj_total": {
                "16 to 19 years": "129808",
                "20 to 24 years": "322270",
                "25 to 44 years": "1244548",
                "45 to 54 years": "650648",
                "55 to 59 years": "308287",
                "60 to 64 years": "208693",
                "65 years and over": "148162",
                "Car, truck, or van - drove alone:": "2502631"
            },
            "worked_at_home": {
                "16 to 19 years": "3606",
                "20 to 24 years": "6380",
                "25 to 44 years": "41637",
                "45 to 54 years": "25148",
                "55 to 59 years": "11611",
                "60 to 64 years": "9432",
                "65 years and over": "11354",
                "total": "109168"
            }
        },
        "Iowa": {
            "g_total": "1574850",
            "id": 19,
            "subj_total": {
                "16 to 19 years": "79725",
                "20 to 24 years": "164661",
                "25 to 44 years": "630385",
                "45 to 54 years": "330250",
                "55 to 59 years": "158000",
                "60 to 64 years": "122523",
                "65 years and over": "89306",
                "Car, truck, or van - drove alone:": "1273415"
            },
            "worked_at_home": {
                "16 to 19 years": "1903",
                "20 to 24 years": "3920",
                "25 to 44 years": "21328",
                "45 to 54 years": "15098",
                "55 to 59 years": "7798",
                "60 to 64 years": "7758",
                "65 years and over": "6443",
                "total": "64248"
            }
        },
        "Kansas": {
            "g_total": "1426252",
            "id": 20,
            "subj_total": {
                "16 to 19 years": "66330",
                "20 to 24 years": "153215",
                "25 to 44 years": "589407",
                "45 to 54 years": "288578",
                "55 to 59 years": "142231",
                "60 to 64 years": "103755",
                "65 years and over": "82736",
                "Car, truck, or van - drove alone:": "1178553"
            },
            "worked_at_home": {
                "16 to 19 years": "1340",
                "20 to 24 years": "3914",
                "25 to 44 years": "21601",
                "45 to 54 years": "13439",
                "55 to 59 years": "6261",
                "60 to 64 years": "5771",
                "65 years and over": "7102",
                "total": "59428"
            }
        },
        "Kentucky": {
            "g_total": "1929752",
            "id": 21,
            "subj_total": {
                "16 to 19 years": "77927",
                "20 to 24 years": "213311",
                "25 to 44 years": "823700",
                "45 to 54 years": "409258",
                "55 to 59 years": "183003",
                "60 to 64 years": "127840",
                "65 years and over": "94713",
                "Car, truck, or van - drove alone:": "1588560"
            },
            "worked_at_home": {
                "16 to 19 years": "1189",
                "20 to 24 years": "2869",
                "25 to 44 years": "22634",
                "45 to 54 years": "14611",
                "55 to 59 years": "6680",
                "60 to 64 years": "6502",
                "65 years and over": "5254",
                "total": "59739"
            }
        },
        "Louisiana": {
            "g_total": "2033248",
            "id": 22,
            "subj_total": {
                "16 to 19 years": "62510",
                "20 to 24 years": "206300",
                "25 to 44 years": "902880",
                "45 to 54 years": "422886",
                "55 to 59 years": "193339",
                "60 to 64 years": "136291",
                "65 years and over": "109042",
                "Car, truck, or van - drove alone:": "1683262"
            },
            "worked_at_home": {
                "16 to 19 years": "241",
                "20 to 24 years": "2262",
                "25 to 44 years": "19109",
                "45 to 54 years": "15700",
                "55 to 59 years": "7512",
                "60 to 64 years": "6527",
                "65 years and over": "5507",
                "total": "56858"
            }
        },
        "Maine": {
            "g_total": "621181",
            "id": 23,
            "subj_total": {
                "16 to 19 years": "24620",
                "20 to 24 years": "57967",
                "25 to 44 years": "228782",
                "45 to 54 years": "143368",
                "55 to 59 years": "70686",
                "60 to 64 years": "52047",
                "65 years and over": "43711",
                "Car, truck, or van - drove alone:": "494624"
            },
            "worked_at_home": {
                "16 to 19 years": "271",
                "20 to 24 years": "1581",
                "25 to 44 years": "10829",
                "45 to 54 years": "8544",
                "55 to 59 years": "5530",
                "60 to 64 years": "4121",
                "65 years and over": "5612",
                "total": "36488"
            }
        },
        "Maryland": {
            "g_total": "2743587",
            "id": 24,
            "subj_total": {
                "16 to 19 years": "90960",
                "20 to 24 years": "249810",
                "25 to 44 years": "1169751",
                "45 to 54 years": "614981",
                "55 to 59 years": "272773",
                "60 to 64 years": "191737",
                "65 years and over": "153575",
                "Car, truck, or van - drove alone:": "2098502"
            },
            "worked_at_home": {
                "16 to 19 years": "2601",
                "20 to 24 years": "5624",
                "25 to 44 years": "45021",
                "45 to 54 years": "36145",
                "55 to 59 years": "15822",
                "60 to 64 years": "11633",
                "65 years and over": "15129",
                "total": "131975"
            }
        },
        "Massachusetts": {
            "g_total": "3532276",
            "id": 25,
            "subj_total": {
                "16 to 19 years": "134153",
                "20 to 24 years": "331778",
                "25 to 44 years": "1444614",
                "45 to 54 years": "786039",
                "55 to 59 years": "361909",
                "60 to 64 years": "262982",
                "65 years and over": "210801",
                "Car, truck, or van - drove alone:": "2492080"
            },
            "worked_at_home": {
                "16 to 19 years": "3397",
                "20 to 24 years": "8591",
                "25 to 44 years": "55018",
                "45 to 54 years": "41894",
                "55 to 59 years": "19038",
                "60 to 64 years": "15159",
                "65 years and over": "20935",
                "total": "164032"
            }
        },
        "Michigan": {
            "g_total": "4383993",
            "id": 26,
            "subj_total": {
                "16 to 19 years": "180342",
                "20 to 24 years": "469410",
                "25 to 44 years": "1777876",
                "45 to 54 years": "996155",
                "55 to 59 years": "456037",
                "60 to 64 years": "299085",
                "65 years and over": "205088",
                "Car, truck, or van - drove alone:": "3630408"
            },
            "worked_at_home": {
                "16 to 19 years": "3579",
                "20 to 24 years": "6588",
                "25 to 44 years": "56940",
                "45 to 54 years": "39705",
                "55 to 59 years": "19766",
                "60 to 64 years": "14345",
                "65 years and over": "17915",
                "total": "158838"
            }
        },
        "Minnesota": {
            "g_total": "2876109",
            "id": 27,
            "subj_total": {
                "16 to 19 years": "126898",
                "20 to 24 years": "281974",
                "25 to 44 years": "1196232",
                "45 to 54 years": "626583",
                "55 to 59 years": "304532",
                "60 to 64 years": "202513",
                "65 years and over": "137377",
                "Car, truck, or van - drove alone:": "2247682"
            },
            "worked_at_home": {
                "16 to 19 years": "7670",
                "20 to 24 years": "12374",
                "25 to 44 years": "52402",
                "45 to 54 years": "35744",
                "55 to 59 years": "18675",
                "60 to 64 years": "14735",
                "65 years and over": "15755",
                "total": "157355"
            }
        },
        "Mississippi": {
            "g_total": "1141953",
            "id": 28,
            "subj_total": {
                "16 to 19 years": "35040",
                "20 to 24 years": "119831",
                "25 to 44 years": "508092",
                "45 to 54 years": "238022",
                "55 to 59 years": "108533",
                "60 to 64 years": "72618",
                "65 years and over": "59817",
                "Car, truck, or van - drove alone:": "974119"
            },
            "worked_at_home": {
                "16 to 19 years": "289",
                "20 to 24 years": "1042",
                "25 to 44 years": "10766",
                "45 to 54 years": "4756",
                "55 to 59 years": "2266",
                "60 to 64 years": "2513",
                "65 years and over": "3483",
                "total": "25115"
            }
        },
        "Missouri": {
            "g_total": "2886690",
            "id": 29,
            "subj_total": {
                "16 to 19 years": "119310",
                "20 to 24 years": "294032",
                "25 to 44 years": "1204072",
                "45 to 54 years": "625108",
                "55 to 59 years": "297583",
                "60 to 64 years": "198394",
                "65 years and over": "148191",
                "Car, truck, or van - drove alone:": "2363226"
            },
            "worked_at_home": {
                "16 to 19 years": "5715",
                "20 to 24 years": "9692",
                "25 to 44 years": "51508",
                "45 to 54 years": "29451",
                "55 to 59 years": "15109",
                "60 to 64 years": "11363",
                "65 years and over": "13692",
                "total": "136530"
            }
        },
        "Montana": {
            "g_total": "479416",
            "id": 30,
            "subj_total": {
                "16 to 19 years": "18147",
                "20 to 24 years": "47891",
                "25 to 44 years": "191475",
                "45 to 54 years": "98542",
                "55 to 59 years": "50301",
                "60 to 64 years": "40978",
                "65 years and over": "32082",
                "Car, truck, or van - drove alone:": "357711"
            },
            "worked_at_home": {
                "16 to 19 years": "706",
                "20 to 24 years": "1181",
                "25 to 44 years": "10818",
                "45 to 54 years": "5804",
                "55 to 59 years": "3332",
                "60 to 64 years": "2751",
                "65 years and over": "4517",
                "total": "29109"
            }
        },
        "Nebraska": {
            "g_total": "997028",
            "id": 31,
            "subj_total": {
                "16 to 19 years": "45467",
                "20 to 24 years": "106335",
                "25 to 44 years": "408146",
                "45 to 54 years": "199530",
                "55 to 59 years": "102415",
                "60 to 64 years": "73999",
                "65 years and over": "61136",
                "Car, truck, or van - drove alone:": "817976"
            },
            "worked_at_home": {
                "16 to 19 years": "1394",
                "20 to 24 years": "2614",
                "25 to 44 years": "13816",
                "45 to 54 years": "7531",
                "55 to 59 years": "4670",
                "60 to 64 years": "3731",
                "65 years and over": "4573",
                "total": "38329"
            }
        },
        "Nevada": {
            "g_total": "1316032",
            "id": 32,
            "subj_total": {
                "16 to 19 years": "37308",
                "20 to 24 years": "134021",
                "25 to 44 years": "596381",
                "45 to 54 years": "285031",
                "55 to 59 years": "112921",
                "60 to 64 years": "84045",
                "65 years and over": "66325",
                "Car, truck, or van - drove alone:": "1024543"
            },
            "worked_at_home": {
                "16 to 19 years": "572",
                "20 to 24 years": "1941",
                "25 to 44 years": "19080",
                "45 to 54 years": "11371",
                "55 to 59 years": "4396",
                "60 to 64 years": "5348",
                "65 years and over": "5397",
                "total": "48105"
            }
        },
        "New Hampshire": {
            "g_total": "648037",
            "id": 33,
            "subj_total": {
                "16 to 19 years": "31983",
                "20 to 24 years": "61691",
                "25 to 44 years": "234992",
                "45 to 54 years": "149400",
                "55 to 59 years": "77166",
                "60 to 64 years": "53099",
                "65 years and over": "39706",
                "Car, truck, or van - drove alone:": "520983"
            },
            "worked_at_home": {
                "16 to 19 years": "1793",
                "20 to 24 years": "1978",
                "25 to 44 years": "11958",
                "45 to 54 years": "12401",
                "55 to 59 years": "7387",
                "60 to 64 years": "4926",
                "65 years and over": "4981",
                "total": "45424"
            }
        },
        "New Jersey": {
            "g_total": "3978088",
            "id": 34,
            "subj_total": {
                "16 to 19 years": "105738",
                "20 to 24 years": "325998",
                "25 to 44 years": "1625396",
                "45 to 54 years": "951697",
                "55 to 59 years": "436481",
                "60 to 64 years": "293291",
                "65 years and over": "239487",
                "Car, truck, or van - drove alone:": "3050518"
            },
            "worked_at_home": {
                "16 to 19 years": "1575",
                "20 to 24 years": "5007",
                "25 to 44 years": "62257",
                "45 to 54 years": "50118",
                "55 to 59 years": "21362",
                "60 to 64 years": "16851",
                "65 years and over": "17883",
                "total": "175053"
            }
        },
        "New Mexico": {
            "g_total": "871327",
            "id": 35,
            "subj_total": {
                "16 to 19 years": "30997",
                "20 to 24 years": "93444",
                "25 to 44 years": "364092",
                "45 to 54 years": "175056",
                "55 to 59 years": "91321",
                "60 to 64 years": "63956",
                "65 years and over": "52461",
                "Car, truck, or van - drove alone:": "709118"
            },
            "worked_at_home": {
                "16 to 19 years": "922",
                "20 to 24 years": "1498",
                "25 to 44 years": "12539",
                "45 to 54 years": "8770",
                "55 to 59 years": "5397",
                "60 to 64 years": "5985",
                "65 years and over": "7165",
                "total": "42276"
            }
        },
        "New York": {
            "g_total": "9667841",
            "id": 36,
            "subj_total": {
                "16 to 19 years": "234565",
                "20 to 24 years": "844779",
                "25 to 44 years": "4278633",
                "45 to 54 years": "2161130",
                "55 to 59 years": "972493",
                "60 to 64 years": "661476",
                "65 years and over": "514765",
                "Car, truck, or van - drove alone:": "4960821"
            },
            "worked_at_home": {
                "16 to 19 years": "6642",
                "20 to 24 years": "18874",
                "25 to 44 years": "130869",
                "45 to 54 years": "90192",
                "55 to 59 years": "42241",
                "60 to 64 years": "34632",
                "65 years and over": "44195",
                "total": "367645"
            }
        },
        "North Carolina": {
            "g_total": "4520809",
            "id": 37,
            "subj_total": {
                "16 to 19 years": "157239",
                "20 to 24 years": "451577",
                "25 to 44 years": "1968725",
                "45 to 54 years": "992880",
                "55 to 59 years": "429079",
                "60 to 64 years": "299965",
                "65 years and over": "221344",
                "Car, truck, or van - drove alone:": "3687937"
            },
            "worked_at_home": {
                "16 to 19 years": "4405",
                "20 to 24 years": "10704",
                "25 to 44 years": "88980",
                "45 to 54 years": "57256",
                "55 to 59 years": "26078",
                "60 to 64 years": "17959",
                "65 years and over": "22162",
                "total": "227544"
            }
        },
        "North Dakota": {
            "g_total": "437559",
            "id": 38,
            "subj_total": {
                "16 to 19 years": "18239",
                "20 to 24 years": "59031",
                "25 to 44 years": "188753",
                "45 to 54 years": "79099",
                "55 to 59 years": "40487",
                "60 to 64 years": "30349",
                "65 years and over": "21601",
                "Car, truck, or van - drove alone:": "358094"
            },
            "worked_at_home": {
                "16 to 19 years": "632",
                "20 to 24 years": "1092",
                "25 to 44 years": "6349",
                "45 to 54 years": "4475",
                "55 to 59 years": "1966",
                "60 to 64 years": "1949",
                "65 years and over": "1640",
                "total": "18103"
            }
        },
        "Ohio": {
            "g_total": "5393979",
            "id": 39,
            "subj_total": {
                "16 to 19 years": "221929",
                "20 to 24 years": "522284",
                "25 to 44 years": "2217666",
                "45 to 54 years": "1179241",
                "55 to 59 years": "563333",
                "60 to 64 years": "402241",
                "65 years and over": "287285",
                "Car, truck, or van - drove alone:": "4495749"
            },
            "worked_at_home": {
                "16 to 19 years": "5129",
                "20 to 24 years": "9127",
                "25 to 44 years": "73234",
                "45 to 54 years": "49156",
                "55 to 59 years": "24179",
                "60 to 64 years": "18848",
                "65 years and over": "20747",
                "total": "200420"
            }
        },
        "Oklahoma": {
            "g_total": "1730466",
            "id": 40,
            "subj_total": {
                "16 to 19 years": "72280",
                "20 to 24 years": "188405",
                "25 to 44 years": "752648",
                "45 to 54 years": "345109",
                "55 to 59 years": "157553",
                "60 to 64 years": "114646",
                "65 years and over": "99825",
                "Car, truck, or van - drove alone:": "1426062"
            },
            "worked_at_home": {
                "16 to 19 years": "3503",
                "20 to 24 years": "4337",
                "25 to 44 years": "23198",
                "45 to 54 years": "14473",
                "55 to 59 years": "6510",
                "60 to 64 years": "5897",
                "65 years and over": "7314",
                "total": "65232"
            }
        },
        "Oregon": {
            "g_total": "1888562",
            "id": 41,
            "subj_total": {
                "16 to 19 years": "60896",
                "20 to 24 years": "180867",
                "25 to 44 years": "841472",
                "45 to 54 years": "395621",
                "55 to 59 years": "176053",
                "60 to 64 years": "139566",
                "65 years and over": "94087",
                "Car, truck, or van - drove alone:": "1351383"
            },
            "worked_at_home": {
                "16 to 19 years": "2333",
                "20 to 24 years": "3443",
                "25 to 44 years": "44858",
                "45 to 54 years": "26732",
                "55 to 59 years": "11911",
                "60 to 64 years": "12354",
                "65 years and over": "14853",
                "total": "116484"
            }
        },
        "Pennsylvania": {
            "g_total": "5911288",
            "id": 42,
            "subj_total": {
                "16 to 19 years": "220304",
                "20 to 24 years": "533756",
                "25 to 44 years": "2367097",
                "45 to 54 years": "1323035",
                "55 to 59 years": "657081",
                "60 to 64 years": "457382",
                "65 years and over": "352633",
                "Car, truck, or van - drove alone:": "4500194"
            },
            "worked_at_home": {
                "16 to 19 years": "6929",
                "20 to 24 years": "13762",
                "25 to 44 years": "92056",
                "45 to 54 years": "62981",
                "55 to 59 years": "28866",
                "60 to 64 years": "22600",
                "65 years and over": "24856",
                "total": "252050"
            }
        },
        "Puerto Rico": {
            "g_total": "999433",
            "id": 72,
            "subj_total": {
                "16 to 19 years": "11321",
                "20 to 24 years": "83633",
                "25 to 44 years": "510167",
                "45 to 54 years": "231299",
                "55 to 59 years": "78285",
                "60 to 64 years": "47760",
                "65 years and over": "36968",
                "Car, truck, or van - drove alone:": "822215"
            },
            "worked_at_home": {
                "16 to 19 years": "319",
                "20 to 24 years": "806",
                "25 to 44 years": "8927",
                "45 to 54 years": "3771",
                "55 to 59 years": "3170",
                "60 to 64 years": "1475",
                "65 years and over": "3432",
                "total": "21900"
            }
        },
        "Rhode Island": {
            "g_total": "484342",
            "id": 44,
            "subj_total": {
                "16 to 19 years": "17692",
                "20 to 24 years": "47344",
                "25 to 44 years": "192369",
                "45 to 54 years": "109183",
                "55 to 59 years": "53941",
                "60 to 64 years": "35368",
                "65 years and over": "28445",
                "Car, truck, or van - drove alone:": "385613"
            },
            "worked_at_home": {
                "16 to 19 years": "472",
                "20 to 24 years": "913",
                "25 to 44 years": "5644",
                "45 to 54 years": "3931",
                "55 to 59 years": "1891",
                "60 to 64 years": "2067",
                "65 years and over": "2010",
                "total": "16928"
            }
        },
        "South Carolina": {
            "g_total": "2112333",
            "id": 45,
            "subj_total": {
                "16 to 19 years": "81827",
                "20 to 24 years": "210824",
                "25 to 44 years": "900763",
                "45 to 54 years": "460179",
                "55 to 59 years": "201420",
                "60 to 64 years": "140875",
                "65 years and over": "116445",
                "Car, truck, or van - drove alone:": "1748898"
            },
            "worked_at_home": {
                "16 to 19 years": "2332",
                "20 to 24 years": "3835",
                "25 to 44 years": "27834",
                "45 to 54 years": "21587",
                "55 to 59 years": "8844",
                "60 to 64 years": "6186",
                "65 years and over": "10088",
                "total": "80706"
            }
        },
        "South Dakota": {
            "g_total": "435764",
            "id": 46,
            "subj_total": {
                "16 to 19 years": "21572",
                "20 to 24 years": "45116",
                "25 to 44 years": "174161",
                "45 to 54 years": "86589",
                "55 to 59 years": "46994",
                "60 to 64 years": "33667",
                "65 years and over": "27665",
                "Car, truck, or van - drove alone:": "352024"
            },
            "worked_at_home": {
                "16 to 19 years": "550",
                "20 to 24 years": "1264",
                "25 to 44 years": "7848",
                "45 to 54 years": "5704",
                "55 to 59 years": "3352",
                "60 to 64 years": "2634",
                "65 years and over": "3618",
                "total": "24970"
            }
        },
        "Tennessee": {
            "g_total": "3002764",
            "id": 47,
            "subj_total": {
                "16 to 19 years": "114168",
                "20 to 24 years": "305465",
                "25 to 44 years": "1283148",
                "45 to 54 years": "651117",
                "55 to 59 years": "290062",
                "60 to 64 years": "196041",
                "65 years and over": "162763",
                "Car, truck, or van - drove alone:": "2526427"
            },
            "worked_at_home": {
                "16 to 19 years": "1072",
                "20 to 24 years": "4258",
                "25 to 44 years": "44160",
                "45 to 54 years": "25050",
                "55 to 59 years": "13502",
                "60 to 64 years": "9231",
                "65 years and over": "14124",
                "total": "111397"
            }
        },
        "Texas": {
            "g_total": "12559656",
            "id": 48,
            "subj_total": {
                "16 to 19 years": "441503",
                "20 to 24 years": "1296540",
                "25 to 44 years": "5789036",
                "45 to 54 years": "2612115",
                "55 to 59 years": "1080779",
                "60 to 64 years": "757067",
                "65 years and over": "582616",
                "Car, truck, or van - drove alone:": "10153731"
            },
            "worked_at_home": {
                "16 to 19 years": "7921",
                "20 to 24 years": "24462",
                "25 to 44 years": "220205",
                "45 to 54 years": "133755",
                "55 to 59 years": "62372",
                "60 to 64 years": "49580",
                "65 years and over": "50654",
                "total": "548949"
            }
        },
        "Utah": {
            "g_total": "1393568",
            "id": 49,
            "subj_total": {
                "16 to 19 years": "83665",
                "20 to 24 years": "189230",
                "25 to 44 years": "646167",
                "45 to 54 years": "237234",
                "55 to 59 years": "103188",
                "60 to 64 years": "78050",
                "65 years and over": "56034",
                "Car, truck, or van - drove alone:": "1058763"
            },
            "worked_at_home": {
                "16 to 19 years": "1363",
                "20 to 24 years": "4338",
                "25 to 44 years": "37602",
                "45 to 54 years": "15284",
                "55 to 59 years": "7714",
                "60 to 64 years": "4674",
                "65 years and over": "6402",
                "total": "77377"
            }
        },
        "Vermont": {
            "g_total": "319961",
            "id": 50,
            "subj_total": {
                "16 to 19 years": "13756",
                "20 to 24 years": "31853",
                "25 to 44 years": "114587",
                "45 to 54 years": "71262",
                "55 to 59 years": "36199",
                "60 to 64 years": "30338",
                "65 years and over": "21966",
                "Car, truck, or van - drove alone:": "245290"
            },
            "worked_at_home": {
                "16 to 19 years": "310",
                "20 to 24 years": "845",
                "25 to 44 years": "5915",
                "45 to 54 years": "4030",
                "55 to 59 years": "2572",
                "60 to 64 years": "2787",
                "65 years and over": "3109",
                "total": "19568"
            }
        },
        "Virginia": {
            "g_total": "4005675",
            "id": 51,
            "subj_total": {
                "16 to 19 years": "137528",
                "20 to 24 years": "394515",
                "25 to 44 years": "1719783",
                "45 to 54 years": "881836",
                "55 to 59 years": "386346",
                "60 to 64 years": "271274",
                "65 years and over": "214393",
                "Car, truck, or van - drove alone:": "3168066"
            },
            "worked_at_home": {
                "16 to 19 years": "2976",
                "20 to 24 years": "8126",
                "25 to 44 years": "69531",
                "45 to 54 years": "51647",
                "55 to 59 years": "22339",
                "60 to 64 years": "15331",
                "65 years and over": "20869",
                "total": "190819"
            }
        },
        "Washington": {
            "g_total": "3322759",
            "id": 53,
            "subj_total": {
                "16 to 19 years": "107155",
                "20 to 24 years": "323223",
                "25 to 44 years": "1480239",
                "45 to 54 years": "702138",
                "55 to 59 years": "322710",
                "60 to 64 years": "227215",
                "65 years and over": "160079",
                "Car, truck, or van - drove alone:": "2405922"
            },
            "worked_at_home": {
                "16 to 19 years": "4345",
                "20 to 24 years": "10489",
                "25 to 44 years": "71635",
                "45 to 54 years": "41940",
                "55 to 59 years": "22679",
                "60 to 64 years": "17487",
                "65 years and over": "21858",
                "total": "190433"
            }
        },
        "West Virginia": {
            "g_total": "705487",
            "id": 54,
            "subj_total": {
                "16 to 19 years": "23931",
                "20 to 24 years": "64404",
                "25 to 44 years": "294477",
                "45 to 54 years": "154612",
                "55 to 59 years": "73459",
                "60 to 64 years": "54092",
                "65 years and over": "40512",
                "Car, truck, or van - drove alone:": "584455"
            },
            "worked_at_home": {
                "16 to 19 years": "847",
                "20 to 24 years": "503",
                "25 to 44 years": "8645",
                "45 to 54 years": "5805",
                "55 to 59 years": "2219",
                "60 to 64 years": "2366",
                "65 years and over": "3063",
                "total": "23448"
            }
        },
        "Wisconsin": {
            "g_total": "2867776",
            "id": 55,
            "subj_total": {
                "16 to 19 years": "132909",
                "20 to 24 years": "304836",
                "25 to 44 years": "1143636",
                "45 to 54 years": "631836",
                "55 to 59 years": "313508",
                "60 to 64 years": "204428",
                "65 years and over": "136623",
                "Car, truck, or van - drove alone:": "2323902"
            },
            "worked_at_home": {
                "16 to 19 years": "3645",
                "20 to 24 years": "6142",
                "25 to 44 years": "40223",
                "45 to 54 years": "31555",
                "55 to 59 years": "15936",
                "60 to 64 years": "9821",
                "65 years and over": "11687",
                "total": "119009"
            }
        },
        "Wyoming": {
            "g_total": "297812",
            "id": 56,
            "subj_total": {
                "16 to 19 years": "14130",
                "20 to 24 years": "28299",
                "25 to 44 years": "127373",
                "45 to 54 years": "58307",
                "55 to 59 years": "31730",
                "60 to 64 years": "22183",
                "65 years and over": "15790",
                "Car, truck, or van - drove alone:": "229309"
            },
            "worked_at_home": {
                "16 to 19 years": "290",
                "20 to 24 years": "572",
                "25 to 44 years": "3431",
                "45 to 54 years": "3428",
                "55 to 59 years": "1249",
                "60 to 64 years": "1467",
                "65 years and over": "1699",
                "total": "12136"
            }
        }
    }
}